Metadata-Version: 2.1
Name: hht
Version: 0.0.1
Summary: A Python implementation of Hilbert-Huang Transform
Home-page: https://github.com/fzhu2e/hht
Author: Feng Zhu
Author-email: fengzhu@usc.edu
License: MIT license
Keywords: hht
Platform: UNKNOWN
Classifier: License :: OSI Approved :: MIT License
Classifier: Natural Language :: English
Classifier: Programming Language :: Python :: 3
Classifier: Programming Language :: Python :: 3.6
